livedict/__init__.py
livedict/core.py
livedict-1.0.4.dist-info/licenses/LICENSE
livedict-1.0.4.dist-info/METADATA
livedict-1.0.4.dist-info/WHEEL
livedict-1.0.4.dist-info/top_level.txt
livedict-1.0.4.dist-info/RECORD
