Metadata-Version: 2.4
Name: livedict
Version: 1.0.4
Summary: Encrypted TTL-based key-value store with sandboxed hooks and optional persistence backends (SQLite/File/Redis).
Home-page: https://github.com/hemanshu03/LiveDict
Author: Hemanshu Vaidya
Author-email: Hemanshu Vaidya <hemanshuvaidya64@gmail.com>
License-Expression: MIT
Project-URL: Homepage, https://github.com/hemanshu03/LiveDict
Project-URL: Source, https://github.com/hemanshu03/LiveDict
Project-URL: Issues, https://github.com/hemanshu03/LiveDict/issues
Classifier: Programming Language :: Python :: 3
Classifier: Operating System :: OS Independent
Requires-Python: >=3.8
License-File: LICENSE
Requires-Dist: pydantic>=1.10
Requires-Dist: cryptography>=3.4
Requires-Dist: redis>=4.0
Requires-Dist: typing-extensions>=4.0
Provides-Extra: dev
Requires-Dist: pytest>=8.0; extra == "dev"
Requires-Dist: pytest-asyncio>=0.23.0; extra == "dev"
Requires-Dist: pytest-cov>=4.0.0; extra == "dev"
Dynamic: author
Dynamic: home-page
Dynamic: license-file
Dynamic: requires-python
